courtesy/__init__.py
courtesy/constants.py
courtesy/errors.py
courtesy/types.py
courtesy/utils/__init__.py
courtesy/utils/io.py
courtesy/utils/code/__init__.py
courtesy/utils/code/projects.py
courtesy/utils/llm/__init__.py
courtesy/utils/llm/chatgpt.py
courtesy/utils/llm/claude.py
courtesy/utils/llm/interfaces.py
courtesy/utils/llm/models.py
courtesy-0.0.0.dev1.dist-info/METADATA
courtesy-0.0.0.dev1.dist-info/WHEEL
courtesy-0.0.0.dev1.dist-info/entry_points.txt
courtesy-0.0.0.dev1.dist-info/RECORD
