Metadata-Version: 2.4
Name: courtesy
Version: 0.0.0.dev1
Summary: An opinionated abstraction layer for the lazy.
Author-email: "K. LeBryce" <k.lebryce@pm.me>
Requires-Python: >=3.10
